gevent-stubs/METADATA.toml
gevent-stubs/__init__.pyi
gevent-stubs/_abstract_linkable.pyi
gevent-stubs/_config.pyi
gevent-stubs/_fileobjectcommon.pyi
gevent-stubs/_greenlet_primitives.pyi
gevent-stubs/_hub_local.pyi
gevent-stubs/_hub_primitives.pyi
gevent-stubs/_ident.pyi
gevent-stubs/_imap.pyi
gevent-stubs/_monitor.pyi
gevent-stubs/_threading.pyi
gevent-stubs/_types.pyi
gevent-stubs/_util.pyi
gevent-stubs/_waiter.pyi
gevent-stubs/ares.pyi
gevent-stubs/backdoor.pyi
gevent-stubs/baseserver.pyi
gevent-stubs/event.pyi
gevent-stubs/events.pyi
gevent-stubs/exceptions.pyi
gevent-stubs/fileobject.pyi
gevent-stubs/greenlet.pyi
gevent-stubs/hub.pyi
gevent-stubs/local.pyi
gevent-stubs/lock.pyi
gevent-stubs/os.pyi
gevent-stubs/pool.pyi
gevent-stubs/py.typed
gevent-stubs/pywsgi.pyi
gevent-stubs/queue.pyi
gevent-stubs/resolver_ares.pyi
gevent-stubs/resolver_thread.pyi
gevent-stubs/select.pyi
gevent-stubs/selectors.pyi
gevent-stubs/server.pyi
gevent-stubs/signal.pyi
gevent-stubs/socket.pyi
gevent-stubs/ssl.pyi
gevent-stubs/subprocess.pyi
gevent-stubs/threadpool.pyi
gevent-stubs/time.pyi
gevent-stubs/timeout.pyi
gevent-stubs/util.pyi
gevent-stubs/win32util.pyi
gevent-stubs/_ffi/__init__.pyi
gevent-stubs/_ffi/loop.pyi
gevent-stubs/_ffi/watcher.pyi
gevent-stubs/libev/__init__.pyi
gevent-stubs/libev/corecext.pyi
gevent-stubs/libev/corecffi.pyi
gevent-stubs/libev/watcher.pyi
gevent-stubs/libuv/__init__.pyi
gevent-stubs/libuv/loop.pyi
gevent-stubs/libuv/watcher.pyi
gevent-stubs/monkey/__init__.pyi
gevent-stubs/monkey/api.pyi
gevent-stubs/resolver/__init__.pyi
gevent-stubs/resolver/ares.pyi
gevent-stubs/resolver/blocking.pyi
gevent-stubs/resolver/cares.pyi
gevent-stubs/resolver/dnspython.pyi
gevent-stubs/resolver/thread.pyi
types_gevent-25.9.0.20251228.dist-info/licenses/LICENSE
types_gevent-25.9.0.20251228.dist-info/METADATA
types_gevent-25.9.0.20251228.dist-info/WHEEL
types_gevent-25.9.0.20251228.dist-info/top_level.txt
types_gevent-25.9.0.20251228.dist-info/RECORD
